run_algrow.py
algrow/__init__.py
algrow/_version.py
algrow/analysis.py
algrow/area_calculation.py
algrow/figurebuilder.py
algrow/gui.py
algrow/hull.py
algrow/image_loading.py
algrow/launch.py
algrow/layout.py
algrow/logging.py
algrow/options.py
algrow/panel.py
algrow/resources/LICENSE.txt
algrow/resources/dependency_licenses.txt
algrow/resources/logo.png
algrow-0.7.0.dist-info/licenses/LICENSE.txt
algrow-0.7.0.dist-info/METADATA
algrow-0.7.0.dist-info/WHEEL
algrow-0.7.0.dist-info/entry_points.txt
algrow-0.7.0.dist-info/top_level.txt
algrow-0.7.0.dist-info/RECORD
