Metadata-Version: 2.4
Name: algrow
Version: 0.7.0
Summary: Image segmentation using alpha hulls, plus automated annotation and growth analysis
Author-email: Marcus McHale <marcus.mchale@universityofgalway.ie>
License: BSD 3-Clause License
Project-URL: Homepage, https://marcusmchale.github.io/algrow/
Classifier: Programming Language :: Python :: 3
Classifier: License :: OSI Approved :: GNU General Public License v3 (GPLv3)
Classifier: Operating System :: OS Independent
Requires-Python: ~=3.10
License-File: LICENSE.txt
Requires-Dist: configargparse
Requires-Dist: numpy
Requires-Dist: pandas
Requires-Dist: scipy
Requires-Dist: scikit-image
Requires-Dist: alphashape
Requires-Dist: matplotlib
Requires-Dist: open3d
Dynamic: license-file
